polyY/__init__.py
polyY/plotly.py
polyy-0.1.1.dist-info/METADATA
polyy-0.1.1.dist-info/WHEEL
polyy-0.1.1.dist-info/top_level.txt
polyy-0.1.1.dist-info/RECORD
