Metadata-Version: 2.4
Name: PolyY
Version: 0.1.1
Summary: A Multi Y axis Plotting Library based on Plotly
Home-page: https://github.com/Nashat90/
Author: Nashat Jumaah Omar
Classifier: Programming Language :: Python :: 3
Classifier: License :: OSI Approved :: MIT License
Classifier: Operating System :: OS Independent
Requires-Python: >=3.8
Requires-Dist: plotly
Requires-Dist: matplotlib
Requires-Dist: pandas
Dynamic: author
Dynamic: classifier
Dynamic: description
Dynamic: description-content-type
Dynamic: home-page
Dynamic: requires-dist
Dynamic: requires-python
Dynamic: summary
